{
 "Week": "2024-09-26",
 "LastWeek": "",
 "X": 0.729065431371011,
 "Programs": [
  {
   "Program": "cmd/go",
   "Version": "go1.23.0",
   "GoVersion": "go1.23.0",
   "GOOS": "linux",
   "GOARCH": "amd64",
   "Counters": {
    "go/goroot:usr-local-go": 31,
    "go/invocations": 31,
    "go/list/flag:json": 20,
    "go/list/flag:m": 10,
    "go/mod-download/flag:json": 1,
    "go/mode:module": 31,
    "go/platform/host/linux/major-version:6": 31,
    "go/platform/host/linux/version:6-1": 31,
    "go/platform/target/goamd64:v1": 31,
    "go/platform/target/goarch:amd64": 31,
    "go/platform/target/goos:linux": 31,
    "go/subcommand:env": 10,
    "go/subcommand:list": 20,
    "go/subcommand:mod-download": 1
   },
   "Stacks": {}
  }
 ],
 "Config": "v0.32.0"
}